dliswriter/__init__.py
dliswriter/configuration.py
dliswriter/logo.png
dliswriter/py.typed
dliswriter/file/__init__.py
dliswriter/file/eflr_sets_dict.py
dliswriter/file/file.py
dliswriter/file/multi_frame_data.py
dliswriter/file/writer.py
dliswriter/logical_record/__init__.py
dliswriter/logical_record/core/__init__.py
dliswriter/logical_record/core/attribute/__init__.py
dliswriter/logical_record/core/attribute/attribute.py
dliswriter/logical_record/core/attribute/subtypes.py
dliswriter/logical_record/core/eflr/__init__.py
dliswriter/logical_record/core/eflr/eflr_item.py
dliswriter/logical_record/core/eflr/eflr_set.py
dliswriter/logical_record/core/iflr/__init__.py
dliswriter/logical_record/core/iflr/iflr.py
dliswriter/logical_record/core/logical_record/__init__.py
dliswriter/logical_record/core/logical_record/logical_record.py
dliswriter/logical_record/core/logical_record/logical_record_bytes.py
dliswriter/logical_record/core/logical_record/segment_attributes.py
dliswriter/logical_record/eflr_types/__init__.py
dliswriter/logical_record/eflr_types/axis.py
dliswriter/logical_record/eflr_types/calibration.py
dliswriter/logical_record/eflr_types/calibration_coefficient.py
dliswriter/logical_record/eflr_types/calibration_measurement.py
dliswriter/logical_record/eflr_types/channel.py
dliswriter/logical_record/eflr_types/comment.py
dliswriter/logical_record/eflr_types/computation.py
dliswriter/logical_record/eflr_types/equipment.py
dliswriter/logical_record/eflr_types/file_header.py
dliswriter/logical_record/eflr_types/frame.py
dliswriter/logical_record/eflr_types/group.py
dliswriter/logical_record/eflr_types/long_name.py
dliswriter/logical_record/eflr_types/message.py
dliswriter/logical_record/eflr_types/no_format.py
dliswriter/logical_record/eflr_types/origin.py
dliswriter/logical_record/eflr_types/parameter.py
dliswriter/logical_record/eflr_types/path.py
dliswriter/logical_record/eflr_types/process.py
dliswriter/logical_record/eflr_types/splice.py
dliswriter-1.2.0.dist-info/METADATA
dliswriter-1.2.0.dist-info/WHEEL
dliswriter-1.2.0.dist-info/licenses/LICENSE
dliswriter-1.2.0.dist-info/RECORD
