Metadata-Version: 2.4
Name: dliswriter
Version: 1.2.0
Summary: An open-source Python package for writing DLIS files.
Project-URL: Homepage, https://github.com/well-id/dliswriter
Project-URL: Documentation, https://well-id-widcdliswriter.readthedocs-hosted.com/
Project-URL: Issues, https://github.com/well-id/dliswriter/issues
Project-URL: Changelog, https://well-id-widcdliswriter.readthedocs-hosted.com/changelog.html
Author: Omer Faruk Sari
Author-email: Dominika Dlugosz <dominika.dlugosz@wellid.no>, Magne Lauritzen <magne.lauritzen@wellid.no>, Kamil Grunwald <kamil.grunwald@wellid.no>
Maintainer-email: Dominika Dlugosz <dominika.dlugosz@wellid.no>
License-File: LICENSE
Keywords: RP66,RP66 v1,binary file IO,data,dlis,dlisio,drilling,oil and gas,petroleum engineering,well imaging,well logging
Classifier: Development Status :: 4 - Beta
Classifier: Intended Audience :: Developers
Classifier: Intended Audience :: Information Technology
Classifier: Intended Audience :: Manufacturing
Classifier: License :: OSI Approved :: MIT License
Classifier: Operating System :: OS Independent
Classifier: Programming Language :: Python :: 3
Classifier: Programming Language :: Python :: 3.9
Classifier: Programming Language :: Python :: 3.10
Classifier: Programming Language :: Python :: 3.11
Classifier: Programming Language :: Python :: 3.12
Classifier: Topic :: File Formats
Requires-Python: >=3.9
Requires-Dist: h5py
Requires-Dist: numpy>=1.19.2
Requires-Dist: progressbar2
Requires-Dist: typing-extensions>=4.0.1
